setup.py
tater/__init__.py
tater.egg-info/PKG-INFO
tater.egg-info/SOURCES.txt
tater.egg-info/dependency_links.txt
tater.egg-info/top_level.txt
tater/base/__init__.py
tater/base/dispatcher.py
tater/base/lexer/__init__.py
tater/base/lexer/exceptions.py
tater/base/lexer/itemclass.py
tater/base/lexer/tokendefs.py
tater/base/lexer/utils.py
tater/base/node/__init__.py
tater/base/node/exceptions.py
tater/base/node/nodespace.py
tater/base/node/resolvers.py
tater/base/visitor/__init__.py
tater/base/visitor/utils.py
tater/core/__init__.py
tater/core/config.py
tater/core/dispatchers.py
tater/core/lexers.py
tater/core/parser.py
tater/core/scanners.py
tater/core/tokentype.py
tater/core/visitors.py
tater/ext/__init__.py
tater/ext/etree.py
tater/ext/legal.py
tater/ext/visitors.py
tater/utils/__init__.py
tater/utils/ansiterm.py
tater/utils/chainmap.py
tater/utils/itemstream.py
tater/utils/lazylist.py
tater/utils/trie.py