Metadata-Version: 1.0
Name: tater
Version: 0.04
Summary: Basic tokenizer and smart-objects implentation.
Home-page: http://twneale.github.com/tater/
Author: Thom Neale
Author-email: twneale@gmail.com
License: MIT
Platform: any
